README.md
pyproject.toml
setup.cfg
setup.py
trainspotting/__init__.py
trainspotting/clients.py
trainspotting/containers.py
trainspotting/factory.py
trainspotting/injector.py
trainspotting/logger.py
trainspotting/utils.py
trainspotting.egg-info/PKG-INFO
trainspotting.egg-info/SOURCES.txt
trainspotting.egg-info/dependency_links.txt
trainspotting.egg-info/top_level.txt