Metadata-Version: 2.1
Name: trainspotting
Version: 1.0.0
Summary: Python Dependency Injector based on interface binding
Home-page: https://github.com/avito-tech/trainspotting
Author: RB387
Author-email: zavadin142@gmail.com
License: MIT
Download-URL: https://github.com/avito-tech/trainspotting/archive/refs/heads/main.zip
Keywords: dependency injection,dependency injector
Platform: UNKNOWN
Classifier: Topic :: Scientific/Engineering
Classifier: Topic :: Software Development :: Build Tools
Classifier: Topic :: Software Development :: Libraries :: Python Modules
Classifier: Topic :: Software Development :: Libraries :: Python Modules
Classifier: License :: OSI Approved :: MIT License
Classifier: Programming Language :: Python :: 3.8
Classifier: Operating System :: MacOS
Classifier: Operating System :: Microsoft :: Windows
Classifier: Operating System :: POSIX
Classifier: Operating System :: Unix
Classifier: Operating System :: OS Independent
Requires-Python: >=3.8
